2task/four_bit_adder_nor.v
module nor_gate(
    input wire a,
    input wire b,
    output wire y
);
    assign y = ~(a | b);
endmodule

module not_gate_nor(
    input wire a,
    output wire y
);
    nor_gate nor_inst(a, a, y);
endmodule

module or_gate_nor(
    input wire a,
    input wire b,
    output wire y
);
    wire w1;
    nor_gate nor1(a, b, w1);
    not_gate_nor not1(w1, y);
endmodule

module and_gate_nor(
    input wire a,
    input wire b,
    output wire y
);
    wire w1, w2;
    not_gate_nor not1(a, w1);
    not_gate_nor not2(b, w2);
    nor_gate nor1(w1, w2, y);
endmodule

module xor_gate_nor(
    input wire a,
    input wire b,
    output wire y
);
    wire w1, w2, w3, w4;
    
    nor_gate nor1(a, b, w1);      
    nor_gate nor2(a, a, w2);       
    nor_gate nor3(b, b, w3);        
    nor_gate nor4(w2, w3, w4);     
    nor_gate nor5(w1, w4, y);       
endmodule

module full_adder_nor(
    input wire a,
    input wire b,
    input wire cin,
    output wire sum,
    output wire cout
);
    wire w1, w2, w3, w4, w5, w6, w7, w8, w9, w10;
    
    xor_gate_nor xor1(a, b, w1);
    xor_gate_nor xor2(w1, cin, sum);
    
    and_gate_nor and1(a, b, w2);           
    and_gate_nor and2(cin, w1, w3);        
    or_gate_nor or1(w2, w3, cout);         
endmodule

module four_bit_adder_nor(
    input wire [3:0] a,
    input wire [3:0] b,
    input wire cin,
    output wire [3:0] sum,
    output wire cout
);
    wire [2:0] carry;
    
    full_adder_nor fa0(
        .a(a[0]),
        .b(b[0]),
        .cin(cin),
        .sum(sum[0]),
        .cout(carry[0])
    );
    
    full_adder_nor fa1(
        .a(a[1]),
        .b(b[1]),
        .cin(carry[0]),
        .sum(sum[1]),
        .cout(carry[1])
    );
    
    full_adder_nor fa2(
        .a(a[2]),
        .b(b[2]),
        .cin(carry[1]),
        .sum(sum[2]),
        .cout(carry[2])
    );
    
    full_adder_nor fa3(
        .a(a[3]),
        .b(b[3]),
        .cin(carry[2]),
        .sum(sum[3]),
        .cout(cout)
    );
endmodule

2task/four_bit_adder_tb.v.v
`timescale 1ns/1ps

module four_bit_adder_tb;
    reg [3:0] a;
    reg [3:0] b;
    reg cin;
    wire [3:0] sum;
    wire cout;
    
    // Промежуточные сигналы для мониторинга
    wire [4:0] result;
    assign result = {cout, sum};
    
    // Экземпляр тестируемого модуля
    four_bit_adder_nor uut(
        .a(a),
        .b(b),
        .cin(cin),
        .sum(sum),
        .cout(cout)
    );
    
    initial begin
        $dumpfile("wave.vcd");
        $dumpvars(0, four_bit_adder_tb);
        
        // Простое сложение
        a = 4'b0000; b = 4'b0000; cin = 0; #10;
        a = 4'b0001; b = 4'b0001; cin = 0; #10;
        a = 4'b0011; b = 4'b0010; cin = 0; #10;
        
        // С переносом между разрядами
        a = 4'b1111; b = 4'b0001; cin = 0; #10;
        a = 4'b1000; b = 4'b1000; cin = 0; #10;
        
        // С входным переносом
        a = 4'b0000; b = 4'b0000; cin = 1; #10;
        a = 4'b1111; b = 4'b0000; cin = 1; #10;
        
        // Максимальные значения
        a = 4'b1111; b = 4'b1111; cin = 0; #10;
        a = 4'b1111; b = 4'b1111; cin = 1; #10;
        
        // Случайные тесты
        a = 4'b1010; b = 4'b0101; cin = 0; #10;
        a = 4'b1100; b = 4'b0011; cin = 1; #10;
        
        $finish;
    end
    
    initial begin
        $monitor("Time: %0t A=%b B=%b Cin=%b → Sum=%b Cout=%b Result=%b",
                 $time, a, b, cin, sum, cout, result);
    end
endmodule

2task/out/wave.vcd
$date
	Wed Oct  8 17:31:51 2025
$end
$version
	Icarus Verilog
$end
$timescale
	1ps
$end
$scope module four_bit_adder_tb $end
$var wire 4 ! sum [3:0] $end
$var wire 5 " result [4:0] $end
$var wire 1 # cout $end
$var reg 4 $ a [3:0] $end
$var reg 4 % b [3:0] $end
$var reg 1 & cin $end
$scope module uut $end
$var wire 4 ' a [3:0] $end
$var wire 4 ( b [3:0] $end
$var wire 1 & cin $end
$var wire 4 ) sum [3:0] $end
$var wire 1 # cout $end
$var wire 3 * carry [2:0] $end
$scope module fa0 $end
$var wire 1 + a $end
$var wire 1 , b $end
$var wire 1 & cin $end
$var wire 1 - w3 $end
$var wire 1 . w2 $end
$var wire 1 / w1 $end
$var wire 1 0 sum $end
$var wire 1 1 cout $end
$scope module and1 $end
$var wire 1 + a $end
$var wire 1 , b $end
$var wire 1 . y $end
$var wire 1 2 w2 $end
$var wire 1 3 w1 $end
$scope module nor1 $end
$var wire 1 . y $end
$var wire 1 2 b $end
$var wire 1 3 a $end
$upscope $end
$scope module not1 $end
$var wire 1 + a $end
$var wire 1 3 y $end
$scope module nor_inst $end
$var wire 1 + a $end
$var wire 1 + b $end
$var wire 1 3 y $end
$upscope $end
$upscope $end
$scope module not2 $end
$var wire 1 , a $end
$var wire 1 2 y $end
$scope module nor_inst $end
$var wire 1 , a $end
$var wire 1 , b $end
$var wire 1 2 y $end
$upscope $end
$upscope $end
$upscope $end
$scope module and2 $end
$var wire 1 & a $end
$var wire 1 - y $end
$var wire 1 4 w2 $end
$var wire 1 5 w1 $end
$var wire 1 / b $end
$scope module nor1 $end
$var wire 1 - y $end
$var wire 1 4 b $end
$var wire 1 5 a $end
$upscope $end
$scope module not1 $end
$var wire 1 & a $end
$var wire 1 5 y $end
$scope module nor_inst $end
$var wire 1 & a $end
$var wire 1 & b $end
$var wire 1 5 y $end
$upscope $end
$upscope $end
$scope module not2 $end
$var wire 1 4 y $end
$var wire 1 / a $end
$scope module nor_inst $end
$var wire 1 4 y $end
$var wire 1 / b $end
$var wire 1 / a $end
$upscope $end
$upscope $end
$upscope $end
$scope module or1 $end
$var wire 1 . a $end
$var wire 1 - b $end
$var wire 1 1 y $end
$var wire 1 6 w1 $end
$scope module nor1 $end
$var wire 1 . a $end
$var wire 1 - b $end
$var wire 1 6 y $end
$upscope $end
$scope module not1 $end
$var wire 1 6 a $end
$var wire 1 1 y $end
$scope module nor_inst $end
$var wire 1 6 a $end
$var wire 1 6 b $end
$var wire 1 1 y $end
$upscope $end
$upscope $end
$upscope $end
$scope module xor1 $end
$var wire 1 + a $end
$var wire 1 , b $end
$var wire 1 / y $end
$var wire 1 7 w4 $end
$var wire 1 8 w3 $end
$var wire 1 9 w2 $end
$var wire 1 : w1 $end
$scope module nor1 $end
$var wire 1 + a $end
$var wire 1 , b $end
$var wire 1 : y $end
$upscope $end
$scope module nor2 $end
$var wire 1 + a $end
$var wire 1 + b $end
$var wire 1 9 y $end
$upscope $end
$scope module nor3 $end
$var wire 1 , a $end
$var wire 1 , b $end
$var wire 1 8 y $end
$upscope $end
$scope module nor4 $end
$var wire 1 9 a $end
$var wire 1 8 b $end
$var wire 1 7 y $end
$upscope $end
$scope module nor5 $end
$var wire 1 : a $end
$var wire 1 7 b $end
$var wire 1 / y $end
$upscope $end
$upscope $end
$scope module xor2 $end
$var wire 1 / a $end
$var wire 1 & b $end
$var wire 1 0 y $end
$var wire 1 ; w4 $end
$var wire 1 < w3 $end
$var wire 1 = w2 $end
$var wire 1 > w1 $end
$scope module nor1 $end
$var wire 1 / a $end
$var wire 1 & b $end
$var wire 1 > y $end
$upscope $end
$scope module nor2 $end
$var wire 1 / a $end
$var wire 1 / b $end
$var wire 1 = y $end
$upscope $end
$scope module nor3 $end
$var wire 1 & a $end
$var wire 1 & b $end
$var wire 1 < y $end
$upscope $end
$scope module nor4 $end
$var wire 1 = a $end
$var wire 1 < b $end
$var wire 1 ; y $end
$upscope $end
$scope module nor5 $end
$var wire 1 > a $end
$var wire 1 ; b $end
$var wire 1 0 y $end
$upscope $end
$upscope $end
$upscope $end
$scope module fa1 $end
$var wire 1 ? a $end
$var wire 1 @ b $end
$var wire 1 A cin $end
$var wire 1 B w3 $end
$var wire 1 C w2 $end
$var wire 1 D w1 $end
$var wire 1 E sum $end
$var wire 1 F cout $end
$scope module and1 $end
$var wire 1 ? a $end
$var wire 1 @ b $end
$var wire 1 C y $end
$var wire 1 G w2 $end
$var wire 1 H w1 $end
$scope module nor1 $end
$var wire 1 C y $end
$var wire 1 G b $end
$var wire 1 H a $end
$upscope $end
$scope module not1 $end
$var wire 1 ? a $end
$var wire 1 H y $end
$scope module nor_inst $end
$var wire 1 ? a $end
$var wire 1 ? b $end
$var wire 1 H y $end
$upscope $end
$upscope $end
$scope module not2 $end
$var wire 1 @ a $end
$var wire 1 G y $end
$scope module nor_inst $end
$var wire 1 @ a $end
$var wire 1 @ b $end
$var wire 1 G y $end
$upscope $end
$upscope $end
$upscope $end
$scope module and2 $end
$var wire 1 A a $end
$var wire 1 B y $end
$var wire 1 I w2 $end
$var wire 1 J w1 $end
$var wire 1 D b $end
$scope module nor1 $end
$var wire 1 B y $end
$var wire 1 I b $end
$var wire 1 J a $end
$upscope $end
$scope module not1 $end
$var wire 1 A a $end
$var wire 1 J y $end
$scope module nor_inst $end
$var wire 1 A a $end
$var wire 1 A b $end
$var wire 1 J y $end
$upscope $end
$upscope $end
$scope module not2 $end
$var wire 1 I y $end
$var wire 1 D a $end
$scope module nor_inst $end
$var wire 1 I y $end
$var wire 1 D b $end
$var wire 1 D a $end
$upscope $end
$upscope $end
$upscope $end
$scope module or1 $end
$var wire 1 C a $end
$var wire 1 B b $end
$var wire 1 F y $end
$var wire 1 K w1 $end
$scope module nor1 $end
$var wire 1 C a $end
$var wire 1 B b $end
$var wire 1 K y $end
$upscope $end
$scope module not1 $end
$var wire 1 K a $end
$var wire 1 F y $end
$scope module nor_inst $end
$var wire 1 K a $end
$var wire 1 K b $end
$var wire 1 F y $end
$upscope $end
$upscope $end
$upscope $end
$scope module xor1 $end
$var wire 1 ? a $end
$var wire 1 @ b $end
$var wire 1 D y $end
$var wire 1 L w4 $end
$var wire 1 M w3 $end
$var wire 1 N w2 $end
$var wire 1 O w1 $end
$scope module nor1 $end
$var wire 1 ? a $end
$var wire 1 @ b $end
$var wire 1 O y $end
$upscope $end
$scope module nor2 $end
$var wire 1 ? a $end
$var wire 1 ? b $end
$var wire 1 N y $end
$upscope $end
$scope module nor3 $end
$var wire 1 @ a $end
$var wire 1 @ b $end
$var wire 1 M y $end
$upscope $end
$scope module nor4 $end
$var wire 1 N a $end
$var wire 1 M b $end
$var wire 1 L y $end
$upscope $end
$scope module nor5 $end
$var wire 1 O a $end
$var wire 1 L b $end
$var wire 1 D y $end
$upscope $end
$upscope $end
$scope module xor2 $end
$var wire 1 D a $end
$var wire 1 A b $end
$var wire 1 E y $end
$var wire 1 P w4 $end
$var wire 1 Q w3 $end
$var wire 1 R w2 $end
$var wire 1 S w1 $end
$scope module nor1 $end
$var wire 1 D a $end
$var wire 1 A b $end
$var wire 1 S y $end
$upscope $end
$scope module nor2 $end
$var wire 1 D a $end
$var wire 1 D b $end
$var wire 1 R y $end
$upscope $end
$scope module nor3 $end
$var wire 1 A a $end
$var wire 1 A b $end
$var wire 1 Q y $end
$upscope $end
$scope module nor4 $end
$var wire 1 R a $end
$var wire 1 Q b $end
$var wire 1 P y $end
$upscope $end
$scope module nor5 $end
$var wire 1 S a $end
$var wire 1 P b $end
$var wire 1 E y $end
$upscope $end
$upscope $end
$upscope $end
$scope module fa2 $end
$var wire 1 T a $end
$var wire 1 U b $end
$var wire 1 V cin $end
$var wire 1 W w3 $end
$var wire 1 X w2 $end
$var wire 1 Y w1 $end
$var wire 1 Z sum $end
$var wire 1 [ cout $end
$scope module and1 $end
$var wire 1 T a $end
$var wire 1 U b $end
$var wire 1 X y $end
$var wire 1 \ w2 $end
$var wire 1 ] w1 $end
$scope module nor1 $end
$var wire 1 X y $end
$var wire 1 \ b $end
$var wire 1 ] a $end
$upscope $end
$scope module not1 $end
$var wire 1 T a $end
$var wire 1 ] y $end
$scope module nor_inst $end
$var wire 1 T a $end
$var wire 1 T b $end
$var wire 1 ] y $end
$upscope $end
$upscope $end
$scope module not2 $end
$var wire 1 U a $end
$var wire 1 \ y $end
$scope module nor_inst $end
$var wire 1 U a $end
$var wire 1 U b $end
$var wire 1 \ y $end
$upscope $end
$upscope $end
$upscope $end
$scope module and2 $end
$var wire 1 V a $end
$var wire 1 W y $end
$var wire 1 ^ w2 $end
$var wire 1 _ w1 $end
$var wire 1 Y b $end
$scope module nor1 $end
$var wire 1 W y $end
$var wire 1 ^ b $end
$var wire 1 _ a $end
$upscope $end
$scope module not1 $end
$var wire 1 V a $end
$var wire 1 _ y $end
$scope module nor_inst $end
$var wire 1 V a $end
$var wire 1 V b $end
$var wire 1 _ y $end
$upscope $end
$upscope $end
$scope module not2 $end
$var wire 1 ^ y $end
$var wire 1 Y a $end
$scope module nor_inst $end
$var wire 1 ^ y $end
$var wire 1 Y b $end
$var wire 1 Y a $end
$upscope $end
$upscope $end
$upscope $end
$scope module or1 $end
$var wire 1 X a $end
$var wire 1 W b $end
$var wire 1 [ y $end
$var wire 1 ` w1 $end
$scope module nor1 $end
$var wire 1 X a $end
$var wire 1 W b $end
$var wire 1 ` y $end
$upscope $end
$scope module not1 $end
$var wire 1 ` a $end
$var wire 1 [ y $end
$scope module nor_inst $end
$var wire 1 ` a $end
$var wire 1 ` b $end
$var wire 1 [ y $end
$upscope $end
$upscope $end
$upscope $end
$scope module xor1 $end
$var wire 1 T a $end
$var wire 1 U b $end
$var wire 1 Y y $end
$var wire 1 a w4 $end
$var wire 1 b w3 $end
$var wire 1 c w2 $end
$var wire 1 d w1 $end
$scope module nor1 $end
$var wire 1 T a $end
$var wire 1 U b $end
$var wire 1 d y $end
$upscope $end
$scope module nor2 $end
$var wire 1 T a $end
$var wire 1 T b $end
$var wire 1 c y $end
$upscope $end
$scope module nor3 $end
$var wire 1 U a $end
$var wire 1 U b $end
$var wire 1 b y $end
$upscope $end
$scope module nor4 $end
$var wire 1 c a $end
$var wire 1 b b $end
$var wire 1 a y $end
$upscope $end
$scope module nor5 $end
$var wire 1 d a $end
$var wire 1 a b $end
$var wire 1 Y y $end
$upscope $end
$upscope $end
$scope module xor2 $end
$var wire 1 Y a $end
$var wire 1 V b $end
$var wire 1 Z y $end
$var wire 1 e w4 $end
$var wire 1 f w3 $end
$var wire 1 g w2 $end
$var wire 1 h w1 $end
$scope module nor1 $end
$var wire 1 Y a $end
$var wire 1 V b $end
$var wire 1 h y $end
$upscope $end
$scope module nor2 $end
$var wire 1 Y a $end
$var wire 1 Y b $end
$var wire 1 g y $end
$upscope $end
$scope module nor3 $end
$var wire 1 V a $end
$var wire 1 V b $end
$var wire 1 f y $end
$upscope $end
$scope module nor4 $end
$var wire 1 g a $end
$var wire 1 f b $end
$var wire 1 e y $end
$upscope $end
$scope module nor5 $end
$var wire 1 h a $end
$var wire 1 e b $end
$var wire 1 Z y $end
$upscope $end
$upscope $end
$upscope $end
$scope module fa3 $end
$var wire 1 i a $end
$var wire 1 j b $end
$var wire 1 k cin $end
$var wire 1 l w3 $end
$var wire 1 m w2 $end
$var wire 1 n w1 $end
$var wire 1 o sum $end
$var wire 1 # cout $end
$scope module and1 $end
$var wire 1 i a $end
$var wire 1 j b $end
$var wire 1 m y $end
$var wire 1 p w2 $end
$var wire 1 q w1 $end
$scope module nor1 $end
$var wire 1 m y $end
$var wire 1 p b $end
$var wire 1 q a $end
$upscope $end
$scope module not1 $end
$var wire 1 i a $end
$var wire 1 q y $end
$scope module nor_inst $end
$var wire 1 i a $end
$var wire 1 i b $end
$var wire 1 q y $end
$upscope $end
$upscope $end
$scope module not2 $end
$var wire 1 j a $end
$var wire 1 p y $end
$scope module nor_inst $end
$var wire 1 j a $end
$var wire 1 j b $end
$var wire 1 p y $end
$upscope $end
$upscope $end
$upscope $end
$scope module and2 $end
$var wire 1 k a $end
$var wire 1 l y $end
$var wire 1 r w2 $end
$var wire 1 s w1 $end
$var wire 1 n b $end
$scope module nor1 $end
$var wire 1 l y $end
$var wire 1 r b $end
$var wire 1 s a $end
$upscope $end
$scope module not1 $end
$var wire 1 k a $end
$var wire 1 s y $end
$scope module nor_inst $end
$var wire 1 k a $end
$var wire 1 k b $end
$var wire 1 s y $end
$upscope $end
$upscope $end
$scope module not2 $end
$var wire 1 r y $end
$var wire 1 n a $end
$scope module nor_inst $end
$var wire 1 r y $end
$var wire 1 n b $end
$var wire 1 n a $end
$upscope $end
$upscope $end
$upscope $end
$scope module or1 $end
$var wire 1 m a $end
$var wire 1 l b $end
$var wire 1 # y $end
$var wire 1 t w1 $end
$scope module nor1 $end
$var wire 1 m a $end
$var wire 1 l b $end
$var wire 1 t y $end
$upscope $end
$scope module not1 $end
$var wire 1 t a $end
$var wire 1 # y $end
$scope module nor_inst $end
$var wire 1 t a $end
$var wire 1 t b $end
$var wire 1 # y $end
$upscope $end
$upscope $end
$upscope $end
$scope module xor1 $end
$var wire 1 i a $end
$var wire 1 j b $end
$var wire 1 n y $end
$var wire 1 u w4 $end
$var wire 1 v w3 $end
$var wire 1 w w2 $end
$var wire 1 x w1 $end
$scope module nor1 $end
$var wire 1 i a $end
$var wire 1 j b $end
$var wire 1 x y $end
$upscope $end
$scope module nor2 $end
$var wire 1 i a $end
$var wire 1 i b $end
$var wire 1 w y $end
$upscope $end
$scope module nor3 $end
$var wire 1 j a $end
$var wire 1 j b $end
$var wire 1 v y $end
$upscope $end
$scope module nor4 $end
$var wire 1 w a $end
$var wire 1 v b $end
$var wire 1 u y $end
$upscope $end
$scope module nor5 $end
$var wire 1 x a $end
$var wire 1 u b $end
$var wire 1 n y $end
$upscope $end
$upscope $end
$scope module xor2 $end
$var wire 1 n a $end
$var wire 1 k b $end
$var wire 1 o y $end
$var wire 1 y w4 $end
$var wire 1 z w3 $end
$var wire 1 { w2 $end
$var wire 1 | w1 $end
$scope module nor1 $end
$var wire 1 n a $end
$var wire 1 k b $end
$var wire 1 | y $end
$upscope $end
$scope module nor2 $end
$var wire 1 n a $end
$var wire 1 n b $end
$var wire 1 { y $end
$upscope $end
$scope module nor3 $end
$var wire 1 k a $end
$var wire 1 k b $end
$var wire 1 z y $end
$upscope $end
$scope module nor4 $end
$var wire 1 { a $end
$var wire 1 z b $end
$var wire 1 y y $end
$upscope $end
$scope module nor5 $end
$var wire 1 | a $end
$var wire 1 y b $end
$var wire 1 o y $end
$upscope $end
$upscope $end
$upscope $end
$upscope $end
$upscope $end
$enddefinitions $end
#0
$dumpvars
1|
1{
1z
0y
1x
1w
1v
0u
1t
1s
1r
1q
1p
0o
0n
0m
0l
0k
0j
0i
1h
1g
1f
0e
1d
1c
1b
0a
1`
1_
1^
1]
1\
0[
0Z
0Y
0X
0W
0V
0U
0T
1S
1R
1Q
0P
1O
1N
1M
0L
1K
1J
1I
1H
1G
0F
0E
0D
0C
0B
0A
0@
0?
1>
1=
1<
0;
1:
19
18
07
16
15
14
13
12
01
00
0/
0.
0-
0,
0+
b0 *
b0 )
b0 (
b0 '
0&
b0 %
b0 $
0#
b0 "
b0 !
$end
#10000
1E
0J
0S
0Q
1A
b1 *
11
b10 "
b10 !
b10 )
00
06
1>
1=
14
1.
0/
17
02
08
03
0:
09
1,
1+
b1 %
b1 (
b1 $
b1 '
#20000
1Z
1J
1S
1Q
0_
0h
0f
10
b101 "
b101 !
b101 )
0E
0A
1V
01
0>
0=
04
b10 *
1F
0P
0B
16
1/
0K
1R
1I
0.
07
1C
0D
1L
12
18
0G
0M
0H
0O
0N
0,
1@
1?
b10 %
b10 (
b11 $
b11 '
#30000
1#
0t
1l
1y
0s
0z
1B
1P
1k
1[
0J
0Q
0_
0f
00
0E
0Z
0`
1A
1V
11
1>
1=
14
b111 *
1F
0S
0R
0I
1e
1W
b10000 "
b0 !
b0 )
0o
06
0/
0K
1D
0g
0^
0|
0{
0r
1.
17
0C
0L
1Y
1n
02
08
1G
1M
0]
0d
0c
0q
0x
0w
1,
0@
1T
1i
b1 %
b1 (
b1111 $
b1111 '
#40000
1_
1h
1f
1s
1|
1z
0V
0k
0o
0F
0[
1J
1S
1Q
0y
0l
0E
1K
b10000 "
b0 !
b0 )
0Z
1`
0A
1{
1r
b0 *
01
0P
0B
0e
0W
0n
16
1R
1I
1g
1^
1m
1u
0.
07
0D
0Y
12
18
0p
0v
13
1:
19
1H
1O
1N
1]
1d
1c
0,
1j
0+
0?
0T
b1000 %
b1000 (
b1000 $
b1000 '
#50000
0#
1t
0m
0u
b1 "
b1 !
b1 )
10
1p
1v
1q
1x
1w
05
0>
0<
0j
0i
1&
b0 %
b0 (
b0 $
b0 '
#60000
1#
0t
1l
1y
0s
0z
1k
1[
0`
1W
1e
0_
0f
1V
1F
0K
1B
1P
0J
0Q
1A
b111 *
11
00
06
1;
1-
0E
0Z
b10000 "
b0 !
b0 )
0o
0=
04
0S
0R
0I
0h
0g
0^
0|
0{
0r
1/
1D
1Y
1n
03
0:
09
0H
0O
0N
0]
0d
0c
0q
0x
0w
1+
1?
1T
1i
b1111 $
b1111 '
#70000
1E
1Z
1o
0P
0B
0e
0W
0y
0l
1>
1=
14
1R
1I
1g
1^
1{
1r
0/
0D
0Y
0n
b11110 "
b1110 !
b1110 )
00
1.
17
1C
1L
1X
1a
1m
1u
0-
0;
02
08
0G
0M
0\
0b
0p
0v
15
1<
1,
1@
1U
1j
0&
b1111 %
b1111 (
#80000
b11111 "
b1111 !
b1111 )
10
05
0>
0<
1&
#90000
1E
1o
1Z
1_
1f
1J
1Q
1s
1z
0P
0B
0y
0l
0e
0W
0V
0A
0k
0F
0R
0I
0#
0{
0r
01
0=
04
b0 *
0[
0g
0^
1K
1D
1t
1n
16
1/
1`
1Y
0C
0L
0m
0u
0.
07
0X
0a
b1111 "
b1111 !
b1111 )
10
1G
1M
1p
1v
13
19
1]
1c
15
0>
1<
0@
0j
0+
0T
0&
b101 %
b101 (
b1010 $
b1010 '
#100000
1#
0t
0o
1l
1y
0s
0z
1k
1[
0`
0Z
1W
1e
0_
0f
1V
1F
0K
0E
1B
1P
0J
0Q
1A
b111 *
11
06
b10000 "
b0 !
b0 )
00
1-
1;
0G
0M
1\
1b
1H
1N
0]
0c
05
0<
1@
0U
0?
1T
1&
b11 %
b11 (
b1100 $
b1100 '
